exoplex
