Metadata-Version: 1.1
Name: exoplex
Version: 1.0.1a1
Summary: exoplanet modeling tool
Home-page: https://github.com/amloren1/ExoPlex
Author: Alejandro Lorenzo
Author-email: amloren1@asu.edu
License: UNKNOWN
Keywords: testing exoplex release
Platform: UNKNOWN
Classifier: Development Status :: 3 - Alpha
Classifier: Intended Audience :: Science/Research
Classifier: Topic :: Scientific/Engineering :: Astronomy
Classifier: License :: OSI Approved :: GNU General Public License v3 (GPLv3)
Classifier: Programming Language :: Python :: 2
Classifier: Programming Language :: Python :: 2.7
